invision_client/__init__.py
invision_client/api_client.py
invision_client/configuration.py
invision_client/exceptions.py
invision_client/invision_api.py
invision_client/model_utils.py
invision_client/rest.py
invision_client/api/__init__.py
invision_client/api/forums_api.py
invision_client/api/members_api.py
invision_client/api/topics_api.py
invision_client/apis/__init__.py
invision_client/model/__init__.py
invision_client/model/core_members_get200_response.py
invision_client/model/field.py
invision_client/model/field_group.py
invision_client/model/fieldgroup.py
invision_client/model/forum.py
invision_client/model/forum_permissions.py
invision_client/model/forums_forums_get200_response.py
invision_client/model/forums_topics_post200_response.py
invision_client/model/forums_topics_post_request.py
invision_client/model/forums_topics_post_request_poll_options_inner.py
invision_client/model/forums_topics_post_request_poll_options_inner_answers_inner.py
invision_client/model/group.py
invision_client/model/member.py
invision_client/model/poll.py
invision_client/model/poll_option_object.py
invision_client/model/poll_option_object_answers_inner.py
invision_client/model/post.py
invision_client/model/post_reactions_inner.py
invision_client/model/question.py
invision_client/model/rank.py
invision_client/model/topic.py
invision_client/models/__init__.py
invision_client_python-1.0.1.dist-info/METADATA
invision_client_python-1.0.1.dist-info/WHEEL
invision_client_python-1.0.1.dist-info/top_level.txt
invision_client_python-1.0.1.dist-info/RECORD
